LICENSE
README.md
setup.cfg
setup.py
src/cmt/__init__.py
src/cmt/project.py
src/cmt/run/__init__.py
src/cmt/run/dhydro.py
src/cmt/utils/__init__.py
src/cmt/utils/log.py
src/cmt/utils/modifyers.py
src/cmt/utils/read_his.py
src/cmt/utils/readers.py
src/cmt/utils/writers.py
src/hydrolib_cmt.egg-info/PKG-INFO
src/hydrolib_cmt.egg-info/SOURCES.txt
src/hydrolib_cmt.egg-info/dependency_links.txt
src/hydrolib_cmt.egg-info/requires.txt
src/hydrolib_cmt.egg-info/top_level.txt
src/stowabui/__init__.py
src/stowabui/meteo_event.py
src/stowabui/data/patronen.xlsx