Metadata-Version: 2.1
Name: hydrolib-cmt
Version: 0.3.0.dev1
Summary: Case Management Tools for DHYDRO
Author: Daniel Tollenaar
Author-email: daniel@d2hydro.nl
Provides-Extra: test
Provides-Extra: docs
License-File: LICENSE
